{
  "( רבנו שמעון בן צמח דוראן (הרשב_ץ": {
    "name_he": "רבנו שמעון בן צמח דוראן הרשבם",
    "era": "modern",
    "locations": [],
    "dates": [
      [
        "1361",
        "1444"
      ],
      [
        "1361",
        "1391"
      ],
      "ה-14"
    ],
    "summary": "משנתו, פועלו והשפעתו של רבנו שמעון בן צמח דוראן (הרשב\"ץ): אדריכל ההנהגה והמחשבה ביהדות צפון אפריקה",
    "text_length": 17371,
    "source_file": "( רבנו שמעון בן צמח דוראן (הרשב_ץ.docx"
  },
  "הבנקאי שהנגיש את המשנה- פנחס קהתי ומהפכת _תורה ומלאכה_": {
    "name_he": "הבנקאי שהנגיש את המשנה- פנחס קהתי ומהפכת תורה ומלאכה",
    "era": "modern",
    "locations": [],
    "dates": [
      [
        "1910",
        "1976"
      ],
      [
        "1955",
        "1964"
      ],
      [
        "1926",
        "1932"
      ]
    ],
    "summary": "הבנקאי שהנגיש את המשנה: פנחס קהתי ומהפכת 'תורה ומלאכה'",
    "text_length": 17487,
    "source_file": "הבנקאי שהנגיש את המשנה- פנחס קהתי ומהפכת _תורה ומלאכה_.docx"
  },
  "המגיד משנה- דמותו, פועלו ומשנתו התורנית של רבי וידאל די טולוזא בראי הדורות": {
    "name_he": "המגיד משנה- דמותו, פועלו ומשנתו התורנית של רבי וידאל די טולוזא בראי הדורות",
    "era": "tannaim",
    "locations": [],
    "dates": [
      "ה-14",
      "ה-14",
      "ה-14"
    ],
    "summary": "המגיד משנה: דמותו, פועלו ומשנתו התורנית של רבי וידאל די טולוזא בראי הדורות",
    "text_length": 16576,
    "source_file": "המגיד משנה- דמותו, פועלו ומשנתו התורנית של רבי וידאל די טולוזא בראי הדורות.docx"
  },
  "הרב אלישע וישליצקי זצ-ל_": {
    "name_he": "הרב אלישע וישליצקי זצ-ל",
    "era": "modern",
    "locations": [],
    "dates": [],
    "summary": "פרופיל מנהיגות: הרב אלישע וישליצקי זצ\"ל – איש החיבורים והענווה",
    "text_length": 22882,
    "source_file": "הרב אלישע וישליצקי זצ-ל_.docx"
  },
  "הרב יוסף בכור שור": {
    "name_he": "הרב יוסף בכור שור",
    "era": "modern",
    "locations": [],
    "dates": [
      [
        "1130",
        "1200"
      ],
      "ה-12",
      "ה-12"
    ],
    "summary": "הרב יוסף בכור שור: דיוקן ביוגרפי ואינטלקטואלי של פרשן בן המאה ה-12",
    "text_length": 41337,
    "source_file": "הרב יוסף בכור שור.docx"
  },
  "הרב יצחק אבוהב הראשון- הגותו ויצירתו על רקע תקופתו": {
    "name_he": "הרב יצחק אבוהב הראשון- הגותו ויצירתו על רקע תקופתו",
    "era": "modern",
    "locations": [],
    "dates": [
      [
        "1347",
        "1351"
      ],
      [
        "1351",
        "1369"
      ],
      "ה-14"
    ],
    "summary": "הרב יצחק אבוהב הראשון: הגותו ויצירתו על רקע תקופתו",
    "text_length": 22609,
    "source_file": "הרב יצחק אבוהב הראשון- הגותו ויצירתו על רקע תקופתו.docx"
  },
  "הרב לוי סעדיה נחמני- משנתו, נבואותיו ומורשתו": {
    "name_he": "הרב לוי סעדיה נחמני- משנתו, נבואותיו ומורשתו",
    "era": "modern",
    "locations": [],
    "dates": [
      [
        "1921",
        "1995"
      ],
      [
        "1950",
        "1959"
      ]
    ],
    "summary": "הרב לוי סעדיה נחמני: משנתו, נבואותיו ומורשתו",
    "text_length": 8874,
    "source_file": "הרב לוי סעדיה נחמני- משנתו, נבואותיו ומורשתו.docx"
  },
  "הרב שלום נח ברזובסקי, בעל ה_נתיבות שלום_- תולדות חייו, משנתו והגותו": {
    "name_he": "הרב שלום נח ברזובסקי, בעל הנתיבות שלום- תולדות חייו, משנתו והגותו",
    "era": "modern",
    "locations": [],
    "dates": [
      [
        "1911",
        "2000"
      ],
      [
        "1911",
        "2000"
      ],
      "ה-20"
    ],
    "summary": "חייו ומשנתו של בעל ה\"נתיבות שלום\": מברנוביץ' ועד ירושלים",
    "text_length": 15511,
    "source_file": "הרב שלום נח ברזובסקי, בעל ה_נתיבות שלום_- תולדות חייו, משנתו והגותו.docx"
  },
  "הריטב_א_ יצירתו, שיטתו הפרשנית ומשנתו ההגותית": {
    "name_he": "הריטבא יצירתו, שיטתו הפרשנית ומשנתו ההגותית",
    "era": "rishonim",
    "locations": [],
    "dates": [
      [
        "1250",
        "1330"
      ],
      "ה-20",
      "ה-21"
    ],
    "summary": "הריטב\"א: יצירתו, שיטתו הפרשנית ומשנתו ההגותית",
    "text_length": 13741,
    "source_file": "הריטב_א_ יצירתו, שיטתו הפרשנית ומשנתו ההגותית.docx"
  },
  "הרשב_ם": {
    "name_he": "הרשבם",
    "era": "rishonim",
    "locations": [],
    "dates": [
      "ה-12",
      "ה-12",
      "ה-12"
    ],
    "summary": "הרשב\"ם: מהפכת הפשט ועיצובה של הפרשנות המחקרית בימי הביניים",
    "text_length": 16311,
    "source_file": "הרשב_ם.docx"
  },
  "יהודה מוסקאטו_ דרשן הרנסנס ומשנתו": {
    "name_he": "יהודה מוסקאטו דרשן הרנסנס ומשנתו",
    "era": "modern",
    "locations": [
      "אלכסנדריה",
      "איטליה",
      "עכו"
    ],
    "dates": [
      [
        "1530",
        "1593"
      ],
      [
        "1558",
        "1560"
      ],
      ". 1530"
    ],
    "summary": "הארכיטקטורה של המחשבה היהודית בתקופת הרנסנס: חייו, כתביו ושיטתו הפילוסופית של רבי יהודה מוסקאטו",
    "text_length": 24825,
    "source_file": "יהודה מוסקאטו_ דרשן הרנסנס ומשנתו.docx"
  },
  "מאור הגולה- פועלו, משנתו התורנית ודמותו ההיסטורית וההגיוגרפית של התנא רבי מאיר": {
    "name_he": "מאור הגולה- פועלו, משנתו התורנית ודמותו ההיסטורית וההגיוגרפית של התנא רבי מאיר",
    "era": "tannaim",
    "locations": [],
    "dates": [
      [
        "1361",
        "1444"
      ],
      [
        "1361",
        "1391"
      ],
      "c0000"
    ],
    "summary": "מאור הגולה: פועלו, משנתו התורנית ודמותו ההיסטורית וההגיוגרפית של התנא רבי מאיר",
    "text_length": 18637,
    "source_file": "מאור הגולה- פועלו, משנתו התורנית ודמותו ההיסטורית וההגיוגרפית של התנא רבי מאיר.docx"
  },
  "מהר_י קולון": {
    "name_he": "מהרי קולון",
    "era": "modern",
    "locations": [],
    "dates": [
      [
        "1420",
        "1495"
      ],
      "ה-15",
      "ה-20"
    ],
    "summary": "פועלו ומשנתו התורנית של מהר\"י קולון: עיצוב ההלכה והמנהג במעבר בין אשכנז לאיטליה",
    "text_length": 9874,
    "source_file": "מהר_י קולון.docx"
  },
  "מהר_ם מינץ": {
    "name_he": "מהרם מינם",
    "era": "rishonim",
    "locations": [],
    "dates": [
      "ה-15",
      "ה-16"
    ],
    "summary": "מנהיגות, הלכה ומסורת באשכנז של שלהי ימי הביניים: פועלו, משנתו התורנית והשפעתו ההיסטורית של מהר\"ם מינץ",
    "text_length": 11007,
    "source_file": "מהר_ם מינץ.docx"
  },
  "מהר_ם מפדובה": {
    "name_he": "מהרם מפדובה",
    "era": "modern",
    "locations": [],
    "dates": [
      [
        "1550",
        "1554"
      ],
      [
        "1521",
        "1597"
      ],
      [
        "1545",
        "1617"
      ]
    ],
    "summary": "פועלו, משנתו התורנית ושושלתו של המהר\"ם מפדובה: מנהיגות יהודית בצומת התרבויות של המאה ה-16",
    "text_length": 14246,
    "source_file": "מהר_ם מפדובה.docx"
  },
  "מן הזדון אל הזכות- טרנספורמציה של כשלונות לנכסים ארגוניים בתורת ה-שם משמואל-": {
    "name_he": "מן הזדון אל הזכות- טרנספורמציה של כשלונות לנכסים ארגוניים בתורת ה-שם משמואל-",
    "era": "modern",
    "locations": [],
    "dates": [
      [
        "1856",
        "1926"
      ],
      [
        "1910",
        "1926"
      ]
    ],
    "summary": "מן הזדון אל הזכות: טרנספורמציה של כשלונות לנכסים ארגוניים בתורת ה\"שם משמואל\"",
    "text_length": 23158,
    "source_file": "מן הזדון אל הזכות- טרנספורמציה של כשלונות לנכסים ארגוניים בתורת ה-שם משמואל-.docx"
  },
  "מסע חייו של הראשון לציון- רבי ישראל יעקב אלגאזי זצ-ל": {
    "name_he": "מסע חייו של הראשון לציון- רבי ישראל יעקב אלגאזי זצ-ל",
    "era": "modern",
    "locations": [],
    "dates": [
      "ה-18",
      "ה-18"
    ],
    "summary": "מסע חייו של הראשון לציון: רבי ישראל יעקב אלגאזי זצ\"ל",
    "text_length": 17403,
    "source_file": "מסע חייו של הראשון לציון- רבי ישראל יעקב אלגאזי זצ-ל.docx"
  },
  "מסעו של מאור- תחנות בחייו ובמורשתו של הרב מרדכי שרעבי זצ-ל": {
    "name_he": "מסעו של מאור- תחנות בחייו ובמורשתו של הרב מרדכי שרעבי זצ-ל",
    "era": "modern",
    "locations": [
      "ירושלים",
      "מצרים",
      "עכו"
    ],
    "dates": [
      [
        "1931",
        "1932"
      ],
      [
        "1908",
        "1932"
      ],
      [
        "1932",
        "1948"
      ]
    ],
    "summary": "מסעו של מאור: תחנות בחייו ובמורשתו של הרב מרדכי שרעבי זצ\"ל",
    "text_length": 44860,
    "source_file": "מסעו של מאור- תחנות בחייו ובמורשתו של הרב מרדכי שרעבי זצ-ל.docx"
  },
  "משנתו ההלכתית ופועלו הציבורי של רבי אברהם קלויזנר (מהרא_ק)": {
    "name_he": "משנתו ההלכתית ופועלו הציבורי של רבי אברהם קלויזנר מהראק",
    "era": "modern",
    "locations": [],
    "dates": [
      [
        "1348",
        "1350"
      ],
      [
        "1915",
        "2007"
      ],
      "ה-14"
    ],
    "summary": "משנתו ההלכתית ופועלו הציבורי של רבי אברהם קלויזנר (מהרא\"ק): מעצב דמותו של מנהג אשכנז בעת החדשה המוקדמת",
    "text_length": 10691,
    "source_file": "משנתו ההלכתית ופועלו הציבורי של רבי אברהם קלויזנר (מהרא_ק).docx"
  },
  "משנתו ההלכתית ופועלו הציבורי של רבי שמשון בן אליעזר (ברוך שאמר)- רנסאנס מלאכת הסת-ם באשכנז וארץ ישראל": {
    "name_he": "משנתו ההלכתית ופועלו הציבורי של רבי שמשון בן אליעזר ברוך שאמר- רנסאנס מלאכת הסת-ם באשכנז וארם ישראל",
    "era": "acharonim",
    "locations": [],
    "dates": [
      "ה-14",
      "ה-14",
      "ה-13"
    ],
    "summary": "משנתו ההלכתית ופועלו הציבורי של רבי שמשון בן אליעזר (ברוך שאמר): רנסאנס מלאכת הסת\"ם באשכנז וארץ ישראל",
    "text_length": 13085,
    "source_file": "משנתו ההלכתית ופועלו הציבורי של רבי שמשון בן אליעזר (ברוך שאמר)- רנסאנס מלאכת הסת-ם באשכנז וארץ ישראל.docx"
  },
  "משפחת אברו_": {
    "name_he": "משפחת אברו",
    "era": "modern",
    "locations": [],
    "dates": [],
    "summary": "היסודות ההיסטוריים והחברתיים של תנועת בעלי התוספות בצרפת של המאה השלוש-עשרה",
    "text_length": 14365,
    "source_file": "משפחת אברו_.docx"
  },
  "סינתזת הגותו ופועלו של הגאון המקובל רבי רפאל משה לוריא זצ-ל": {
    "name_he": "סינתזת הגותו ופועלו של הגאון המקובל רבי רפאל משה לוריא זצ-ל",
    "era": "modern",
    "locations": [],
    "dates": [
      "ה-80"
    ],
    "summary": "סינתזת הגותו ופועלו של הגאון המקובל רבי רפאל משה לוריא זצ\"ל",
    "text_length": 19632,
    "source_file": "סינתזת הגותו ופועלו של הגאון המקובל רבי רפאל משה לוריא זצ-ל.docx"
  },
  "פועלו ומשנתו התורנית והמדעית של רבי דוד גנז- היסטוריוגרפיה, אסטרונומיה ומפגש התרבויות בפראג של תקופת הרנסנס": {
    "name_he": "פועלו ומשנתו התורנית והמדעית של רבי דוד גנז- היסטוריוגרפיה, אסטרונומיה ומפגש התרבויות בפראג של תקופת הרנסנס",
    "era": "rishonim",
    "locations": [],
    "dates": [
      [
        "1541",
        "1613"
      ],
      [
        "1541",
        "1613"
      ],
      [
        "1891",
        "1972"
      ]
    ],
    "summary": "פועלו ומשנתו התורנית והמדעית של רבי דוד גנז: היסטוריוגרפיה, אסטרונומיה ומפגש התרבויות בפראג של תקופת הרנסנס",
    "text_length": 14413,
    "source_file": "פועלו ומשנתו התורנית והמדעית של רבי דוד גנז- היסטוריוגרפיה, אסטרונומיה ומפגש התרבויות בפראג של תקופת הרנסנס.docx"
  },
  "פועלו ומשנתו התורנית של הרמב_ן": {
    "name_he": "פועלו ומשנתו התורנית של הרמבן",
    "era": "modern",
    "locations": [],
    "dates": [
      [
        "1194",
        "1270"
      ],
      "ה-13",
      "ה-13"
    ],
    "summary": "פועלו ומשנתו התורנית של הרמב\"ן: מנהיגות, הלכה, ומיסטיקה במפנה המאה ה-13",
    "text_length": 14386,
    "source_file": "פועלו ומשנתו התורנית של הרמב_ן.docx"
  },
  "פועלו ומשנתו התורנית של מהר_ם מרוטנבורג": {
    "name_he": "פועלו ומשנתו התורנית של מהרם מרוטנבורג",
    "era": "modern",
    "locations": [],
    "dates": [
      "ה-13",
      "ה-13",
      "ה-13"
    ],
    "summary": "פועלו ומשנתו התורנית של מהר\"ם מרוטנבורג: ציר מרכזי בעיצוב עולם ההלכה והקהילה באשכנז",
    "text_length": 13016,
    "source_file": "פועלו ומשנתו התורנית של מהר_ם מרוטנבורג.docx"
  },
  "פועלו ומשנתו התורנית של רבי ישראל מקרמז_- הארכיטקטורה של -הגהות אשר-י- ועיצוב פסיקת אשכנז המאוחרת": {
    "name_he": "פועלו ומשנתו התורנית של רבי ישראל מקרמז- הארכיטקטורה של -הגהות אשר-י- ועיצוב פסיקת אשכנז המאוחרת",
    "era": "modern",
    "locations": [],
    "dates": [
      [
        "1348",
        "1349"
      ],
      [
        "1520",
        "1523"
      ],
      "ה-14"
    ],
    "summary": "פועלו ומשנתו התורנית של רבי ישראל מקרמז': הארכיטקטורה של \"הגהות אשר\"י\" ועיצוב פסיקת אשכנז המאוחרת",
    "text_length": 15615,
    "source_file": "פועלו ומשנתו התורנית של רבי ישראל מקרמז_- הארכיטקטורה של -הגהות אשר-י- ועיצוב פסיקת אשכנז המאוחרת.docx"
  },
  "פועלו ומשנתו של הרב בן-ציון מאיר חי עוזיאל- עיון ביסודות הגותו הציונית-הלכתית": {
    "name_he": "פועלו ומשנתו של הרב בן-ציון מאיר חי עוזיאל- עיון ביסודות הגותו הציונית-הלכתית",
    "era": "modern",
    "locations": [],
    "dates": [
      [
        "1880",
        "1953"
      ],
      [
        "1880",
        "1953"
      ],
      [
        "1533",
        "1600"
      ]
    ],
    "summary": "פועלו ומשנתו של הרב בן-ציון מאיר חי עוזיאל: עיון ביסודות הגותו הציונית-הלכתית",
    "text_length": 38673,
    "source_file": "פועלו ומשנתו של הרב בן-ציון מאיר חי עוזיאל- עיון ביסודות הגותו הציונית-הלכתית.docx"
  },
  "ר_ חסדאי קרשקש_": {
    "name_he": "ר חסדאי קרשקש",
    "era": "tannaim",
    "locations": [],
    "dates": [
      [
        "1340",
        "1410"
      ],
      [
        "1340",
        "1410"
      ],
      [
        "1270",
        "1348"
      ]
    ],
    "summary": "השפעות פילוסופיות ומדעיות על כתביו ההלכתיים של ר' חסדאי קרשקש וחוגו",
    "text_length": 66795,
    "source_file": "ר_ חסדאי קרשקש_.docx"
  },
  "ר_ יצחק בן אשר הלוי (ריב_א) - מחקר מעמיק": {
    "name_he": "ר יצחק בן אשר הלוי ריבא - מחקר מעמיק",
    "era": "rishonim",
    "locations": [],
    "dates": [
      "ה-11",
      "ה-12"
    ],
    "summary": "ר' יצחק בן אשר הלוי (ריב\"א הראשון): דמותו ופועלו של אבי תנועת התוספות באשכנז",
    "text_length": 3807,
    "source_file": "ר_ יצחק בן אשר הלוי (ריב_א) - מחקר מעמיק.docx"
  },
  "ראב_ד מפושקייר": {
    "name_he": "ראבד מפושקייר",
    "era": "tannaim",
    "locations": [],
    "dates": [
      "ה-12"
    ],
    "summary": "מאמר זה סוקר את קורות חייו, יצירתו הספרותית והשפעתו ההיסטורית של רבי אברהם בן דוד מפושקיירה (הראב\"ד השלישי), שהיה דמות מפתח ביהדות צרפת של המאה ה-12. הטקסט מדגיש את מפעלו הפרשני וההלכתי הכביר, הכולל את חיבורו המפורסם \"בעלי הנפש\" לצד השגותיו הביקורתיות על הרמב\"ם, שנועדו לשמר את הדינמיות של התלמוד כנג...",
    "text_length": 17701,
    "source_file": "ראב_ד מפושקייר.docx"
  },
  "רב ד_ר אברהם לבני_ מטא-היסטוריה, פולמוס וגאולת ישראל": {
    "name_he": "רב דר אברהם לבני מטא-היסטוריה, פולמוס וגאולת ישראל",
    "era": "modern",
    "locations": [],
    "dates": [],
    "summary": "רב ד\"ר אברהם לבני: מטא-היסטוריה, פולמוס וגאולת ישראל",
    "text_length": 9707,
    "source_file": "רב ד_ר אברהם לבני_ מטא-היסטוריה, פולמוס וגאולת ישראל.docx"
  },
  "רבי אלעזר אזכרי- משורר, מקובל ומנהיג רוחני בצפת של המאה ה-16": {
    "name_he": "רבי אלעזר אזכרי- משורר, מקובל ומנהיג רוחני בצפת של המאה ה-16",
    "era": "tannaim",
    "locations": [],
    "dates": [
      [
        "1570",
        "1572"
      ],
      "ה-16",
      "ה-16"
    ],
    "summary": "רבי אלעזר אזכרי: משורר, מקובל ומנהיג רוחני בצפת של המאה ה-16",
    "text_length": 8806,
    "source_file": "רבי אלעזר אזכרי- משורר, מקובל ומנהיג רוחני בצפת של המאה ה-16.docx"
  },
  "רבי יהודה בר עילאי": {
    "name_he": "רבי יהודה בר עילאי",
    "era": "tannaim",
    "locations": [],
    "dates": [],
    "summary": "משנתו התורנית, הנהגותיו ופועלו הציבורי של רבי יהודה בר עילאי: מחקר היסטורי והלכתי מקיף",
    "text_length": 13884,
    "source_file": "רבי יהודה בר עילאי.docx"
  },
  "רבי יהודה החסיד- דמותו, הגותו וצוואתו – ניתוח ותובנות": {
    "name_he": "רבי יהודה החסיד- דמותו, הגותו וצוואתו – ניתוח ותובנות",
    "era": "modern",
    "locations": [],
    "dates": [
      "ה-12",
      "ה-13",
      "ה-19"
    ],
    "summary": "עולמו ההגותי, יצירתו התורנית ופועלו הציבורי של רבי יהודה החסיד: ניתוח היסטורי, דוקטרינרי והלכתי",
    "text_length": 28445,
    "source_file": "רבי יהודה החסיד- דמותו, הגותו וצוואתו – ניתוח ותובנות.docx"
  },
  "רבי יעקב בן אשר - בעל הטורים": {
    "name_he": "רבי יעקב בן אשר - בעל הטורים",
    "era": "modern",
    "locations": [],
    "dates": [
      "ה-14",
      "ה-13",
      "ה-15"
    ],
    "summary": "רבי יעקב בן אשר - בעל הטורים",
    "text_length": 13926,
    "source_file": "רבי יעקב בן אשר - בעל הטורים.docx"
  },
  "רבי יעקב לנדא": {
    "name_he": "רבי יעקב לנדא",
    "era": "modern",
    "locations": [],
    "dates": [
      "ה-15",
      "ה-20"
    ],
    "summary": "המקור היחיד שסופק לי הוא מסמך העיון שכותרתו \"מסורת הפסיקה וההנהגה של רבי יעקב לנדא: ממהפכת ה'אגור' ועד לרבנות בני ברק\". מסמך זה עוסק בשתי דמויות היסטוריות בעלות אותו השם: רבי יעקב לנדא שחי במאה ה-15 וחיבר את קודקס ההלכה \"ספר האגור\", ורבי יעקב לנדא שחי במאה ה-20 וכיהן כרבה של העיר בני ברק.",
    "text_length": 882,
    "source_file": "רבי יעקב לנדא.docx"
  },
  "רבי יעקב מרגליות": {
    "name_he": "רבי יעקב מרגליות",
    "era": "modern",
    "locations": [],
    "dates": [
      "ה-15",
      "ה-15",
      "ה-16"
    ],
    "summary": "משנתו התורנית ופועלו הציבורי של רבי יעקב בן משה מרגליות מנירנברג: ניתוח היסטורי-הלכתי של מעבר המרכז התורני מאשכנז לפולין",
    "text_length": 17185,
    "source_file": "רבי יעקב מרגליות.docx"
  },
  "רבי ישראל נג_ארה": {
    "name_he": "רבי ישראל נגארה",
    "era": "rishonim",
    "locations": [],
    "dates": [
      [
        "1625",
        "1628"
      ],
      [
        "1550",
        "1625"
      ],
      [
        "1625",
        "1628"
      ]
    ],
    "summary": "Рабби Исраэль Наджара: Многогранное наследие за пределами поэзии. Исследование галахических, этических и гомилетических трудов",
    "text_length": 29877,
    "source_file": "רבי ישראל נג_ארה.docx"
  },
  "רבי מאיר בן ברוך הלוי (מהר-ם סג-ל)": {
    "name_he": "רבי מאיר בן ברוך הלוי מהר-ם סג-ל",
    "era": "modern",
    "locations": [],
    "dates": [
      [
        "1348",
        "1349"
      ],
      [
        "1348",
        "1349"
      ],
      [
        "1381",
        "1392"
      ]
    ],
    "summary": "משנתו, פועלו והשפעתו ההיסטורית של רבי מאיר בן ברוך הלוי (מהר\"ם סג\"ל)",
    "text_length": 16187,
    "source_file": "רבי מאיר בן ברוך הלוי (מהר-ם סג-ל).docx"
  },
  "רבי מנחם עזריה מפאנו": {
    "name_he": "רבי מנחם עזריה מפאנו",
    "era": "modern",
    "locations": [],
    "dates": [
      [
        "5308",
        "5380"
      ],
      [
        "1548",
        "1620"
      ],
      "ה-16"
    ],
    "summary": "רב פעלים ומקובל אלוקי: דמותו, משנתו והשפעתו ההיסטורית של רבי מנחם עזריה מפאנו",
    "text_length": 12336,
    "source_file": "רבי מנחם עזריה מפאנו.docx"
  },
  "רבי שמשון בן אליעזר (ברוך שאמר)- רנסאנס מלאכת הסת-ם": {
    "name_he": "רבי שמשון בן אליעזר ברוך שאמר- רנסאנס מלאכת הסת-ם",
    "era": "acharonim",
    "locations": [],
    "dates": [
      "ה-14",
      "ה-14",
      "ה-13"
    ],
    "summary": "משנתו ההלכתית ופועלו הציבורי של רבי שמשון בן אליעזר (ברוך שאמר): רנסאנס מלאכת הסת\"ם באשכנז וארץ ישראל",
    "text_length": 12402,
    "source_file": "רבי שמשון בן אליעזר (ברוך שאמר)- רנסאנס מלאכת הסת-ם.docx"
  },
  "רבי שראל מקרמז_- הארכיטקטורה של -הגהות אשר-י-": {
    "name_he": "רבי שראל מקרמז- הארכיטקטורה של -הגהות אשר-י-",
    "era": "modern",
    "locations": [],
    "dates": [
      [
        "1348",
        "1349"
      ],
      [
        "1520",
        "1523"
      ],
      "ה-14"
    ],
    "summary": "פועלו ומשנתו התורנית של רבי ישראל מקרמז': הארכיטקטורה של \"הגהות אשר\"י\" ועיצוב פסיקת אשכנז המאוחרת",
    "text_length": 14150,
    "source_file": "רבי שראל מקרמז_- הארכיטקטורה של -הגהות אשר-י-.docx"
  },
  "רבינו בחיי בן אשר": {
    "name_he": "רבינו בחיי בן אשר",
    "era": "rishonim",
    "locations": [],
    "dates": [
      [
        "1269",
        "1340"
      ],
      ".1255",
      ".2021"
    ],
    "summary": "הדרך הזוהרת: ניתוח מקיף של המערכת הפרשנית והאתית של רבינו בחיי בן אשר",
    "text_length": 23929,
    "source_file": "רבינו בחיי בן אשר.docx"
  },
  "רבינו דוד בר ראובן בונפיד": {
    "name_he": "רבינו דוד בר ראובן בונפיד",
    "era": "rishonim",
    "locations": [],
    "dates": [],
    "summary": "רבינו דוד בר ראובן בונפיד",
    "text_length": 5945,
    "source_file": "רבינו דוד בר ראובן בונפיד.docx"
  },
  "רבינו זרחיה הלוי (הרז-ה)- פועלו ומשנתו התורנית של בעל -המאור-": {
    "name_he": "רבינו זרחיה הלוי הרז-ה- פועלו ומשנתו התורנית של בעל -המאור-",
    "era": "rishonim",
    "locations": [],
    "dates": [
      "ה-12",
      "ה-12",
      "ה-12"
    ],
    "summary": "רבינו זרחיה הלוי (הרז\"ה): פועלו ומשנתו התורנית של בעל \"המאור\"",
    "text_length": 23179,
    "source_file": "רבינו זרחיה הלוי (הרז-ה)- פועלו ומשנתו התורנית של בעל -המאור-.docx"
  },
  "רבינו זרחיה הלוי (הרז_ה)": {
    "name_he": "רבינו זרחיה הלוי הרזה",
    "era": "amoraim",
    "locations": [],
    "dates": [
      "ה-12",
      "ה-12",
      "ה-12"
    ],
    "summary": "רבינו זרחיה הלוי -רז\"ה",
    "text_length": 36476,
    "source_file": "רבינו זרחיה הלוי (הרז_ה).docx"
  },
  "רבנו בחיי אבן פקודה": {
    "name_he": "רבנו בחיי אבן פקודה",
    "era": "modern",
    "locations": [],
    "dates": [
      [
        "1161",
        "1180"
      ],
      "ה-11",
      "ה-11"
    ],
    "summary": "רבנו בחיי אבן פקודה: בין תיאולוגיה רציונליסטית, אסקטיקה סופית וטיהור הלב",
    "text_length": 20632,
    "source_file": "רבנו בחיי אבן פקודה.docx"
  },
  "רבנו יצחק בר ששת (הריב-ש)": {
    "name_he": "רבנו יצחק בר ששת הריב-ש",
    "era": "modern",
    "locations": [],
    "dates": [
      "ה-14",
      "ה-15",
      "ה-14"
    ],
    "summary": "פועלו, משנתו והנהגתו של רבנו יצחק בר ששת (הריב\"ש): מחקר מקיף על דמותו כחוליה מקשרת בין ספרד לצפון אפריקה",
    "text_length": 10353,
    "source_file": "רבנו יצחק בר ששת (הריב-ש).docx"
  },
  "רבנו משה בן מימון": {
    "name_he": "רבנו משה בן מימון",
    "era": "tannaim",
    "locations": [],
    "dates": [
      "ה-13"
    ],
    "summary": "מקור זה מהווה מחקר מעמיק הסוקר את תולדות חייו ויצירתו המהפכנית של רבנו משה בן מימון (הרמב\"ם), ומציג אותו כדמות רב-ממדית שאיחדה בין הלכה, פילוסופיה ומדע. הטקסט מנתח את המבנה הלוגי של חיבוריו המרכזיים, החל מפירוש המשנה ועד לקודקס ההלכתי המונומנטלי \"משנה תורה\", תוך הדגשת שאיפתו של הרמב\"ם להנגיש את הידע...",
    "text_length": 14679,
    "source_file": "רבנו משה בן מימון.docx"
  },
  "רבנו ניסים הר_ן": {
    "name_he": "רבנו ניסים הרן",
    "era": "rishonim",
    "locations": [],
    "dates": [
      [
        "1347",
        "1351"
      ],
      "ה-14",
      "ה-14"
    ],
    "summary": "רבנו נסים בן ראובן גירונדי (הר\"ן): מנהיגות, הלכה ומחשבה בשלהי תור הזהב",
    "text_length": 13530,
    "source_file": "רבנו ניסים הר_ן.docx"
  },
  "רות המואבייה": {
    "name_he": "רות המואבייה",
    "era": "amoraim",
    "locations": [],
    "dates": [],
    "summary": "מאמר זה מציע ניתוח מעמיק ורב-ממדי של דמות רות המואבייה, תוך התמקדות בתיקון ההיסטורי והרוחני שהיא מחוללת לשושלת סדום ומואב באמצעות מידת החסד יוצאת הדופן שלה. הטקסט בוחן את המורכבות ההלכתית של גיורה דרך סוגיית \"גר קטן\", ומדגיש כיצד הקפדתה על פרטי המצוות וצניעותה בשדה הפכו אותה למודל של \"אשת חיל\" הראוי...",
    "text_length": 13504,
    "source_file": "רות המואבייה.docx"
  },
  "תובנות מרכזיות על הגותו וחייו של רבי משה חיים לוצאטו (הרמח-ל)": {
    "name_he": "תובנות מרכזיות על הגותו וחייו של רבי משה חיים לוצאטו הרמח-ל",
    "era": "modern",
    "locations": [],
    "dates": [
      [
        "1707",
        "1746"
      ],
      "ה-18",
      "ה-18"
    ],
    "summary": "תובנות מרכזיות על הגותו וחייו של רבי משה חיים לוצאטו (הרמח\"ל)",
    "text_length": 28267,
    "source_file": "תובנות מרכזיות על הגותו וחייו של רבי משה חיים לוצאטו (הרמח-ל).docx"
  },
  "תמצית תובנות- פילון האלכסנדרוני, הגותו והשפעתו": {
    "name_he": "תמצית תובנות- פילון האלכסנדרוני, הגותו והשפעתו",
    "era": "rishonim",
    "locations": [],
    "dates": [
      "ה-16"
    ],
    "summary": "תמצית תובנות: פילון האלכסנדרוני, הגותו והשפעתו",
    "text_length": 25778,
    "source_file": "תמצית תובנות- פילון האלכסנדרוני, הגותו והשפעתו.docx"
  }
}